compllments/__init__.py
compllments/config.py
compllments/cron
compllments/data/personal_audio_files_will_go_here.txt
compllments/main.py
compllments/models/add_models_here.txt
compllments/utils/__init__.py
compllments/utils/create_audio.py
compllments/utils/model.py
compllments/utils/providers.py
compllments/utils/template.py
compllments/utils/texter.py
compllments-0.2.0.dist-info/entry_points.txt
compllments-0.2.0.dist-info/WHEEL
compllments-0.2.0.dist-info/METADATA
compllments-0.2.0.dist-info/RECORD
