Metadata-Version: 2.1
Name: compllments
Version: 0.2.0
Summary: Send nice texts to your friends using LLMs
Author: Austin Botelho
Author-email: austinbotelho@nyu.edu
Requires-Python: >=3.8.1,<3.11
Classifier: Programming Language :: Python :: 3
Classifier: Programming Language :: Python :: 3.9
Classifier: Programming Language :: Python :: 3.10
Requires-Dist: accelerate (>=0.19.0,<0.20.0)
Requires-Dist: bitsandbytes (>=0.39.0,<0.40.0)
Requires-Dist: cffi (>=1.15.1,<2.0.0)
Requires-Dist: click (>=8.1.3,<9.0.0)
Requires-Dist: einops (>=0.6.1,<0.7.0)
Requires-Dist: emoji (>=2.4.0,<3.0.0)
Requires-Dist: ftransc (>=7.0.3,<8.0.0)
Requires-Dist: langchain (>=0.0.180,<0.0.181)
Requires-Dist: lxml (>=4.9.2,<5.0.0)
Requires-Dist: num2words (>=0.5.12,<0.6.0)
Requires-Dist: numba (==0.56.4)
Requires-Dist: numpy (==1.22.4)
Requires-Dist: openai (>=0.27.7,<0.28.0)
Requires-Dist: pandas (>=2.0.2,<3.0.0)
Requires-Dist: poethepoet (>=0.20.0,<0.21.0)
Requires-Dist: pydub (>=0.25.1,<0.26.0)
Requires-Dist: pynput (>=1.7.6,<2.0.0)
Requires-Dist: pywhatkit (>=5.4,<6.0)
Requires-Dist: transformers (>=4.29.2,<5.0.0)
Requires-Dist: twilio (>=8.2.1,<9.0.0)
